LICENSE
README.rst
setup.py
RSI_RI.egg-info/PKG-INFO
RSI_RI.egg-info/SOURCES.txt
RSI_RI.egg-info/dependency_links.txt
RSI_RI.egg-info/requires.txt
RSI_RI.egg-info/top_level.txt
rsi_ri/__init__.py
rsi_ri/client.py
rsi_ri/echo_server.py
rsi_ri/examples.py
rsi_ri/log.py
rsi_ri/network.py
rsi_ri/server.py
rsi_ri/tools.py
rsi_ri.egg-info/PKG-INFO
rsi_ri.egg-info/SOURCES.txt
rsi_ri.egg-info/dependency_links.txt
rsi_ri.egg-info/top_level.txt