Metadata-Version: 2.1
Name: RSI-RI
Version: 1.0.4
Summary: A Python layer to simply usage of the KUKA RobotSensorInterface
Home-page: https://github.com/Divvet/RSI-RI
Author: Adam Morgan
Author-email: adam.j.morgan@swansea.ac.uk
License: GPLv3
Platform: UNKNOWN
License-File: LICENSE
